soundpadrc/__init__.py
soundpadrc/soundpadrc.py
soundpadrc-1.0.0.dist-info/licenses/LICENSE
soundpadrc-1.0.0.dist-info/METADATA
soundpadrc-1.0.0.dist-info/WHEEL
soundpadrc-1.0.0.dist-info/top_level.txt
soundpadrc-1.0.0.dist-info/RECORD
