Metadata-Version: 2.4
Name: soundpadrc
Version: 1.0.0
Summary: Control Soundpad with Python
Author-email: r4b2 <pypi@r4b2.de>
Project-URL: Homepage, https://github.com/yggdrion/soundpadrc
Project-URL: Issues, https://github.com/yggdrion/soundpadrc/issues
Classifier: Programming Language :: Python :: 3
Classifier: Operating System :: Microsoft :: Windows
Requires-Python: >=3.8
License-File: LICENSE
Requires-Dist: xmltodict
Dynamic: license-file
